envai/__init__.py
envai/utils.py
envai-0.1.5.dist-info/LICENSE
envai-0.1.5.dist-info/METADATA
envai-0.1.5.dist-info/WHEEL
envai-0.1.5.dist-info/top_level.txt
envai-0.1.5.dist-info/RECORD
